selenium_browser/__init__.py
selenium_browser/selenium_browser.py
selenium_browser/utils.py
selenium_browser/__resources/__init__.py
selenium_browser/__resources/constants.py
selenium_browser/addons/__init__.py
selenium_browser/addons/addon_utils.py
selenium_browser/addons/models/__init__.py
selenium_browser/addons/models/addon_install_settings.py
selenium_browser/core/__init__.py
selenium_browser/core/browser_cookies.py
selenium_browser/core/browser_find_funcs.py
selenium_browser/core/browser_js_functions.py
selenium_browser/core/browser_properties.py
selenium_browser/core/browser_webdriver_wraps.py
selenium_browser/core/browser_webelement_functions.py
selenium_browser/models/__init__.py
selenium_browser/models/capabilities.py
selenium_browser-0.0.15.dist-info/LICENSE
selenium_browser-0.0.15.dist-info/METADATA
selenium_browser-0.0.15.dist-info/WHEEL
selenium_browser-0.0.15.dist-info/top_level.txt
selenium_browser-0.0.15.dist-info/RECORD
