Metadata-Version: 2.1
Name: selenium_browser
Version: 0.0.15
Summary: selenium_browser
Home-page: https://github.com/kkristof200/selenium_browser
Author: Kristóf-Attila Kovács
License: UNKNOWN
Platform: UNKNOWN
Classifier: Programming Language :: Python :: 3.4
Classifier: Programming Language :: Python :: 3.5
Classifier: Programming Language :: Python :: 3.6
Classifier: Programming Language :: Python :: 3.7
Classifier: Programming Language :: Python :: 3.8
Classifier: Programming Language :: Python :: 3.9
Classifier: License :: OSI Approved :: MIT License
Classifier: Operating System :: OS Independent
Requires-Python: >=3.4
License-File: LICENSE
